{
  "baseUrl": "https://fibicoi.fibiweb.com/coi",
  "fibiUrl": "https://fibicoi.fibiweb.com/fibii",
  "authUrl": "https://fibicoi.fibiweb.com/auth",
  "opaUrl": "https://fibicoi.fibiweb.com/opa",
  "formUrl":"https://fibicoi.fibiweb.com/",
  "fibiCOIConnectUrl": "https://fibicoi.fibiweb.com/",
  "entityURL": "/entity",
  "enableSSO": false,
  "enableGraph": true,
  "isElasticAuthentiaction": true,
  "elasticUserName": "elastic",
  "elasticDelimiter": ":",
  "elasticPassword": "Polsol_@#7889",
  "elasticAuthScheme": "Basic",
  "elasticIndexUrl":"https://fibicoi.fibiweb.com/elastic_8/",
  "indexValue": "",
  "EXTERNAL_APPLICATION_BASE_URL": "",
  "EXTERNAL_DEV_PROPOSAL_URL": "",
  "EXTERNAL_AWARD_URL": "",
  "EXTERNAL_IP_URL": "",
  "EXTERNAL_PERSON_URL": "",
  "EXTERNAL_ROLODEX_PERSON_URL": ""
  "fibiApplicationUrl":"https://qa.fibiweb.com/fibi"
}
